./.gitignore
./LICENSE
./PKG-INFO
./PUBLISH.sh
./README.md
./package.json
./pyproject.toml
./test_tibet.py
./tibet_server.py
mcp_server_tibet-1.0.0.dist-info/METADATA
mcp_server_tibet-1.0.0.dist-info/WHEEL
mcp_server_tibet-1.0.0.dist-info/entry_points.txt
mcp_server_tibet-1.0.0.dist-info/licenses/LICENSE
mcp_server_tibet-1.0.0.dist-info/RECORD
