Metadata-Version: 2.4
Name: mcp-server-tibet
Version: 1.0.0
Summary: TIBET MCP Server - Transaction/Interaction-Based Evidence Trail. Trust & provenance for AI systems.
Project-URL: Homepage, https://humotica.com
Project-URL: Repository, https://github.com/humotica/mcp-tibet
Project-URL: Documentation, https://github.com/humotica/mcp-tibet#readme
Author-email: Claude & Jasper <info@humotica.com>
License-Expression: MIT
License-File: LICENSE
Keywords: ai-safety,audit,humoticaos,mcp,model-context-protocol,provenance,tibet,trust
Classifier: Development Status :: 4 - Beta
Classifier: Intended Audience :: Developers
Classifier: License :: OSI Approved :: MIT License
Classifier: Programming Language :: Python :: 3
Classifier: Programming Language :: Python :: 3.10
Classifier: Programming Language :: Python :: 3.11
Classifier: Programming Language :: Python :: 3.12
Classifier: Topic :: Security
Classifier: Topic :: Software Development :: Libraries
Requires-Python: >=3.10
Requires-Dist: mcp>=1.0.0
Requires-Dist: pydantic>=2.0.0
